{
  "_class": "symbolMaster",
  "allowsOverrides": true,
  "backgroundColor": {
    "_class": "color",
    "alpha": 1,
    "blue": 1,
    "green": 1,
    "red": 1
  },
  "booleanOperation": 0,
  "changeIdentifier": 464,
  "clippingMaskMode": 0,
  "do_objectID": "6F185242-0CFD-4EF0-B104-5CC4677B1A20",
  "exportOptions": {
    "_class": "exportOptions",
    "exportFormats": [
    ],
    "includedLayerIds": [
    ],
    "layerOptions": 0,
    "shouldTrim": false
  },
  "frame": {
    "_class": "rect",
    "constrainProportions": false,
    "height": 315,
    "width": 770,
    "x": 35425,
    "y": 1214
  },
  "grid": {
    "_class": "simpleGrid",
    "gridSize": 8,
    "isEnabled": false,
    "thickGridTimes": 10
  },
  "groupLayout": {
    "_class": "MSImmutableFreeformGroupLayout"
  },
  "hasBackgroundColor": false,
  "hasClickThrough": true,
  "hasClippingMask": false,
  "horizontalRulerData": {
    "_class": "rulerData",
    "base": 0,
    "guides": [
    ]
  },
  "includeBackgroundColorInExport": true,
  "includeBackgroundColorInInstance": false,
  "includeInCloudUpload": true,
  "isFixedToViewport": false,
  "isFlippedHorizontal": false,
  "isFlippedVertical": false,
  "isFlowHome": false,
  "isLocked": false,
  "isVisible": true,
  "layerListExpandedType": 0,
  "layers": [
    {
      "class": "group",
      "id": "DF9D0C18-FC75-4934-B0D3-FF14509356B7"
    }
  ],
  "name": "Module/Chat/Profile Panel Tablet",
  "nameIsFixed": false,
  "overrideProperties": [
    {
      "_class": "MSImmutableOverrideProperty",
      "canOverride": true,
      "overrideName": "B2BF0F5E-9E01-4D6C-988C-96414D8A238B_stringValue"
    },
    {
      "_class": "MSImmutableOverrideProperty",
      "canOverride": true,
      "overrideName": "7FF3D86B-CD5A-4CCE-A753-B899AB4DEA3A_symbolID"
    },
    {
      "_class": "MSImmutableOverrideProperty",
      "canOverride": true,
      "overrideName": "767776F2-C8C5-4472-AD0E-C10DCF6D9C73_stringValue"
    },
    {
      "_class": "MSImmutableOverrideProperty",
      "canOverride": true,
      "overrideName": "CA060276-4FE6-48FC-B574-F8E35EC85C0F_textStyle"
    },
    {
      "_class": "MSImmutableOverrideProperty",
      "canOverride": true,
      "overrideName": "A0D83D7E-12C1-4C73-A98F-2F62CE53AA96_textStyle"
    },
    {
      "_class": "MSImmutableOverrideProperty",
      "canOverride": true,
      "overrideName": "A9F97E5E-286A-4959-B48A-1D829DC3D1C4_stringValue"
    },
    {
      "_class": "MSImmutableOverrideProperty",
      "canOverride": true,
      "overrideName": "D41D5964-2841-48A1-BCE2-D8788EC97566_textStyle"
    },
    {
      "_class": "MSImmutableOverrideProperty",
      "canOverride": true,
      "overrideName": "1619C746-8149-4D7D-A6AB-523A094B0C55_stringValue"
    },
    {
      "_class": "MSImmutableOverrideProperty",
      "canOverride": true,
      "overrideName": "3B5EBFA1-7BD3-4632-B21C-8695C5D6D6EF_stringValue"
    },
    {
      "_class": "MSImmutableOverrideProperty",
      "canOverride": true,
      "overrideName": "FB7158D0-7246-4E7C-B4D4-646BE61675B4_stringValue"
    },
    {
      "_class": "MSImmutableOverrideProperty",
      "canOverride": true,
      "overrideName": "9FF88208-CC2F-455B-9269-A84BC6E92A53_stringValue"
    },
    {
      "_class": "MSImmutableOverrideProperty",
      "canOverride": true,
      "overrideName": "2C1B07AC-3032-464A-97D3-ED58054B7F50_textStyle"
    },
    {
      "_class": "MSImmutableOverrideProperty",
      "canOverride": true,
      "overrideName": "B2BF0F5E-9E01-4D6C-988C-96414D8A238B_textStyle"
    },
    {
      "_class": "MSImmutableOverrideProperty",
      "canOverride": true,
      "overrideName": "3B5EBFA1-7BD3-4632-B21C-8695C5D6D6EF_textStyle"
    },
    {
      "_class": "MSImmutableOverrideProperty",
      "canOverride": true,
      "overrideName": "D41D5964-2841-48A1-BCE2-D8788EC97566_stringValue"
    },
    {
      "_class": "MSImmutableOverrideProperty",
      "canOverride": true,
      "overrideName": "767776F2-C8C5-4472-AD0E-C10DCF6D9C73_textStyle"
    },
    {
      "_class": "MSImmutableOverrideProperty",
      "canOverride": true,
      "overrideName": "225B48B4-8B93-4E0D-8032-E877EFA55894_symbolID"
    },
    {
      "_class": "MSImmutableOverrideProperty",
      "canOverride": true,
      "overrideName": "E1E81608-F0C7-41BE-AF2E-B7EE7859B94E_textStyle"
    },
    {
      "_class": "MSImmutableOverrideProperty",
      "canOverride": true,
      "overrideName": "FB7158D0-7246-4E7C-B4D4-646BE61675B4_textStyle"
    },
    {
      "_class": "MSImmutableOverrideProperty",
      "canOverride": true,
      "overrideName": "BDA5A739-3DC3-4D08-9E80-ADAAD12C48A5_textStyle"
    },
    {
      "_class": "MSImmutableOverrideProperty",
      "canOverride": true,
      "overrideName": "2C1B07AC-3032-464A-97D3-ED58054B7F50_stringValue"
    },
    {
      "_class": "MSImmutableOverrideProperty",
      "canOverride": true,
      "overrideName": "DF7C9E24-39A3-4BAD-A94F-2FA602E754BA_textStyle"
    },
    {
      "_class": "MSImmutableOverrideProperty",
      "canOverride": true,
      "overrideName": "9FF88208-CC2F-455B-9269-A84BC6E92A53_textStyle"
    },
    {
      "_class": "MSImmutableOverrideProperty",
      "canOverride": true,
      "overrideName": "CA060276-4FE6-48FC-B574-F8E35EC85C0F_stringValue"
    },
    {
      "_class": "MSImmutableOverrideProperty",
      "canOverride": true,
      "overrideName": "BDA5A739-3DC3-4D08-9E80-ADAAD12C48A5_stringValue"
    },
    {
      "_class": "MSImmutableOverrideProperty",
      "canOverride": true,
      "overrideName": "42D16E1A-49BF-4483-B47E-F717C5AE9A68_symbolID"
    },
    {
      "_class": "MSImmutableOverrideProperty",
      "canOverride": true,
      "overrideName": "A9F97E5E-286A-4959-B48A-1D829DC3D1C4_textStyle"
    },
    {
      "_class": "MSImmutableOverrideProperty",
      "canOverride": true,
      "overrideName": "A0D83D7E-12C1-4C73-A98F-2F62CE53AA96_stringValue"
    },
    {
      "_class": "MSImmutableOverrideProperty",
      "canOverride": true,
      "overrideName": "DF7C9E24-39A3-4BAD-A94F-2FA602E754BA_stringValue"
    },
    {
      "_class": "MSImmutableOverrideProperty",
      "canOverride": true,
      "overrideName": "5D69C026-6CFD-4423-8BC8-1484C1E37961_symbolID"
    },
    {
      "_class": "MSImmutableOverrideProperty",
      "canOverride": true,
      "overrideName": "E18D59F5-8364-4BE1-AB44-8DFA2C6AA6D7_symbolID"
    },
    {
      "_class": "MSImmutableOverrideProperty",
      "canOverride": true,
      "overrideName": "1619C746-8149-4D7D-A6AB-523A094B0C55_textStyle"
    },
    {
      "_class": "MSImmutableOverrideProperty",
      "canOverride": true,
      "overrideName": "E1E81608-F0C7-41BE-AF2E-B7EE7859B94E_stringValue"
    }
  ],
  "presetDictionary": {
  },
  "resizesContent": true,
  "resizingConstraint": 63,
  "resizingType": 0,
  "rotation": 0,
  "shouldBreakMaskChain": true,
  "style": {
    "_class": "style",
    "blur": {
      "_class": "blur",
      "center": "{0.5, 0.5}",
      "isEnabled": false,
      "motionAngle": 0,
      "radius": 10,
      "saturation": 1,
      "type": 0
    },
    "borderOptions": {
      "_class": "borderOptions",
      "dashPattern": [
      ],
      "isEnabled": true,
      "lineCapStyle": 0,
      "lineJoinStyle": 0
    },
    "borders": [
    ],
    "colorControls": {
      "_class": "colorControls",
      "brightness": 0,
      "contrast": 1,
      "hue": 0,
      "isEnabled": false,
      "saturation": 1
    },
    "contextSettings": {
      "_class": "graphicsContextSettings",
      "blendMode": 0,
      "opacity": 1
    },
    "do_objectID": "ADA0DB47-2DE9-4A09-830A-89DF6B46CC4D",
    "endMarkerType": 0,
    "fills": [
    ],
    "innerShadows": [
    ],
    "miterLimit": 10,
    "shadows": [
    ],
    "startMarkerType": 0,
    "windingRule": 1
  },
  "symbolID": "0F4B7B9A-046B-4426-8439-15065FD52988",
  "userInfo": {
    "com.animaapp.stc-sketch-plugin": {
      "kModelPropertiesKey": {
      }
    }
  },
  "verticalRulerData": {
    "_class": "rulerData",
    "base": 0,
    "guides": [
    ]
  }
}